matteopy/__init__.py
matteopy/__version__.py
matteopy/play.py
matteopy/data/matteo1.m4a
matteopy/data/matteo2.m4a
matteopy/data/matteo3.m4a
matteopy/data/matteo4.m4a
matteopy/data/matteo5.m4a
matteopy/data/matteo6.m4a
matteopy/data/matteo7.m4a
matteopy/data/matteo8.m4a
matteopy/data/matteo9.m4a
matteopy/utils/__init__.py
matteopy/utils/package_data.py
matteopy-0.2.3.data/scripts/matteo
matteopy-0.2.3.dist-info/METADATA
matteopy-0.2.3.dist-info/WHEEL
matteopy-0.2.3.dist-info/top_level.txt
matteopy-0.2.3.dist-info/RECORD
