Metadata-Version: 2.1
Name: matteopy
Version: 0.2.3
Summary: Ey!
Home-page: https://github.com/grburgess/matteopy.git
Author: J. Michael Burgess
Author-email: jmichaelburgess@gmail.com
License: BSD
Platform: UNKNOWN
Requires-Python: >=3.5.0
Requires-Dist: numpy
Requires-Dist: pydub
